chayan/__init__.py
chayan/loader.py
chayan/nifty_data.py
chayan-2.0.1.dist-info/METADATA
chayan-2.0.1.dist-info/WHEEL
chayan-2.0.1.dist-info/top_level.txt
chayan-2.0.1.dist-info/RECORD
