Metadata-Version: 2.1
Name: chayan
Version: 2.0.1
Summary: Library to fetch nifty midcap, largecap and smallcap stocks.
Home-page: https://github.com/sharmaak/chayan
Author: Amit Kumar Sharma
Author-email: amit.official@gmail.com
Classifier: Development Status :: 4 - Beta
Classifier: Intended Audience :: Developers
Classifier: Programming Language :: Python :: 3
Classifier: Operating System :: POSIX :: Linux
Requires-Python: >=3.8
Requires-Dist: requests
